googlesearch/__init__.py
googlesearch/__main__.py
googlesearch/gsearch.py
ds_popularity-0.1.dist-info/METADATA
ds_popularity-0.1.dist-info/WHEEL
ds_popularity-0.1.dist-info/top_level.txt
ds_popularity-0.1.dist-info/RECORD
