Metadata-Version: 2.1
Name: ds-popularity
Version: 0.1
Summary: UNKNOWN
Home-page: https://github.com/matthewashby/DS-popularity
Author: DS
Author-email: matt@ashby.co.uk
License: NA
Platform: UNKNOWN
Requires-Dist: cachetools (==3.1.0)
Requires-Dist: google-api-python-client (==1.7.8)
Requires-Dist: google-auth (==1.6.3)
Requires-Dist: google-auth-httplib2 (==0.0.3)
Requires-Dist: httplib2 (==0.12.3)
Requires-Dist: pyasn1 (==0.4.5)
Requires-Dist: pyasn1-modules (==0.2.5)
Requires-Dist: rsa (==4.0)
Requires-Dist: six (==1.12.0)
Requires-Dist: uritemplate (==3.0.0)
